vinput/__init__.py
vinput/_binding.py
vinput/lib/libvinput.dll.dat
vinput/lib/libvinput.dylib.dat
vinput/lib/libvinput.so.dat
vinput-0.6.2.dist-info/LICENSE
vinput-0.6.2.dist-info/METADATA
vinput-0.6.2.dist-info/WHEEL
vinput-0.6.2.dist-info/top_level.txt
vinput-0.6.2.dist-info/RECORD
