Metadata-Version: 2.1
Name: vinput
Version: 0.6.2
Summary: Python bindings for the libvinput library
Author-email: Slendi <slendi@socopon.com>
License: AGPLv3
Project-URL: Homepage, https://github.com/xslendix/libvinput.py
License-File: LICENSE
